sonofman/__init__.py
sonofman/pdcurses.dll
sonofman/pdcurses.lib
sonofman/som_cachetab.py
sonofman/som_config.py
sonofman/som_dal.py
sonofman/som_main.py
sonofman/som_unicurses.py
sonofman/som_util.py
sonofman/som_version.py
sonofman/som_winutil.py
sonofman/data/.DS_Store
sonofman/data/__init__.py
sonofman/data/bible.db
sonofman/data/sonofman.ini
sonofman/data/sonofman_install.ini
sonofman/data/strings-de.xml
sonofman/data/strings-en.xml
sonofman/data/strings-es.xml
sonofman/data/strings-fr.xml
sonofman/data/strings-it.xml
sonofman/data/strings-pt.xml
sonofman-3.5.0.dist-info/LICENSE
sonofman-3.5.0.dist-info/METADATA
sonofman-3.5.0.dist-info/WHEEL
sonofman-3.5.0.dist-info/entry_points.txt
sonofman-3.5.0.dist-info/top_level.txt
sonofman-3.5.0.dist-info/RECORD
