Metadata-Version: 2.1
Name: sonofman
Version: 3.5.0
Summary: Bible multi languages, free, offline, no advertising, in English, French, Italian, Spanish, Portuguese for Terminal. Easy to use with quick searches, parables, articles, cross references, favorites, history
Home-page: https://gitlab.com/hotlittlewhitedog/BibleMultiTheSonOfMan
Author: hotlittlewhitedog
Author-email: hotlittlewhitedog@gmail.com
License: GPL3
Project-URL: Bug Tracker, https://gitlab.com/hotlittlewhitedog/BibleMultiTheSonOfMan/issues
Project-URL: Documentation, https://gitlab.com/hotlittlewhitedog/BibleMultiTheSonOfMan
Project-URL: Source Code, https://gitlab.com/hotlittlewhitedog/BibleMultiTheSonOfMan
Keywords: bible,multi,bible multi,biblia,bíblia,bibbia,bibel,reading,terminal,ncurses,CLI,english,français,italiano,española,german,portuguese,arabic,russian,chinese,japanese,python,mac,linux,windows,termux,cygwin,raspberry,arm,sonofman,jesus,color
Classifier: Development Status :: 5 - Production/Stable
Classifier: Environment :: Console
Classifier: Environment :: Console :: Curses
Classifier: Environment :: MacOS X
Classifier: Environment :: X11 Applications
Classifier: Intended Audience :: Education
Classifier: Intended Audience :: Religion
Classifier: Programming Language :: Python
Classifier: Programming Language :: Python :: 3
Classifier: Programming Language :: Python :: 3.7
Classifier: Programming Language :: Python :: 3.8
Classifier: Programming Language :: Python :: 3.9
Classifier: Programming Language :: Python :: 3.10
Classifier: Programming Language :: Python :: 3.11
Classifier: Programming Language :: Python :: 3.12
Classifier: License :: OSI Approved :: GNU General Public License v3 (GPLv3)
Classifier: Natural Language :: French
Classifier: Natural Language :: English
Classifier: Natural Language :: Portuguese
Classifier: Natural Language :: Spanish
Classifier: Natural Language :: Italian
Classifier: Operating System :: POSIX :: Linux
Classifier: Operating System :: Microsoft :: Windows
Classifier: Operating System :: MacOS :: MacOS X
Classifier: Topic :: Religion
License-File: LICENSE
Requires-Dist: setuptools
Requires-Dist: xerox
Requires-Dist: wcwidth
